{
  "normal": {
    "guessCount": 6
  },
  "infinite": {
    "levelCount": 12,
    "startLength": 3,
    "startingPool": 4,
    "rewards": {
      "easy": 4,
      "medium": 3,
      "hard": 2
    }
  },
  "adventure": {
    "levelCount": 25,
    "startingLives": {
      "easy": 6,
      "normal": 6,
      "hard": 4
    },
    "startingPerks": {
      "easy": { "perkA": 1 },
      "normal": {},
      "hard": {}
    },
    "bossLevels": {
      "5": 10,
      "10": 11,
      "15": 12,
      "20": 13,
      "25": 14
    },
    "nonBossRamp": [4, 4, 5, 5, 5, 6, 6, 7, 7, 7, 8, 8, 8, 9, 9, 9, 9, 10, 10, 10],
    "rewards": {
      "level": 10
    },
    "bossReward": {
      "easy": 25,
      "normal": 20,
      "hard": 15
    },
    "shop": {
      "lifePrice": 3,
      "hintPrice": 6,
      "skipPrice": 50,
      "insurance": {
        "firstPrice": 10,
        "rebuyPrice": 20,
        "premium": 2,
        "reviveLives": 4
      },
      "perkA": {
        "price": 60,
        "upgradePrice": 80,
        "livesPerLevel": 1,
        "upgradedLivesPerLevel": 2
      },
      "perkB": {
        "price": 60,
        "upgradePrice": 80,
        "guessThreshold": 3,
        "upgradedGuessThreshold": 4
      }
    }
  }
}
